{
    "label": "先知+效果 Oracles+ Effects",
    "entries": {
        "Effect: Beast Curse": {
            "name": "效果: 野兽秘示域诅咒 Beast Curse"
        },
        "Effect: Beast Temp HP": {
            "name": "效果: 野兽秘示域临时生命值 Beast Temp HP"
        },
        "Effect: Beast Temp HP (Finesse)": {
            "name": "效果: 野兽秘示域临时生命值 Beast Temp HP (娴熟)"
        },
        "Effect: Curse of Unsupressable Brilliance": {
            "name": "效果: 难遮光辉诅咒 Curse of Unsupressable Brilliance"
        },
        "Effect: Fate Curse": {
            "name": "效果: 命运秘示域诅咒 Fate Curse"
        },
        "Effect: Fate Temp HP": {
            "name": "效果: 命运秘示域临时生命值 Fate Temp HP"
        },
        "Effect: Frost Curse": {
            "name": "效果: 霜冻秘示域诅咒 Frost Curse"
        },
        "Effect: Mountain Curse": {
            "name": "效果: 山脉秘示域诅咒 Mountain Curse"
        },
        "Glimpse Future Marker": {
            "name": "预知未来标记 Glimpse Future Marker"
        },
        "Spell Effect:  Glimpse Future": {
            "name": "法术效果: 预知未来 Glimpse Future"
        },
        "Spell Effect: Doomsaying": {
            "name": "法术效果: 末日预言 Doomsaying",
            "description": "<p>效果来自@Compendium[oracles.oracles-revelation-spells.mkwJihuJVPCv0Z1X]{末日预言 Doomsaying}。</p>\n<p>下次目标进行攻击检定或是豁免掷骰时，必须骰两次并取更低的结果，之后法术结束。</p>"
        },
        "Spell Effect: Fractal Frosting (9th)": {
            "name": "法术效果: 分型结霜 Fractal Frosting (9环)",
            "description": "<p>效果来自@Compendium[oracles.oracles-revelation-spells.VVBmn8DPIInJDxjw]{分型结霜 Fractal Frosting}.</p>\n<p>当你在分型结霜的持续时间内施放<em>冰冻射线</em>时，成功的攻击会让目标在速度上承受-5尺的状态减值，或是大成功时承受-15尺的状态减值。.</p>"
        },
        "Spell Effect: Monstrous Charge": {
            "name": "法术效果: 骇人冲锋 Monstrous Charge",
            "description": "<p>效果来自@UUID[Compendium.oracles.oracles-revelation-spells.3VzkXeFQLaBqyNkc]{骇人冲锋 Monstrous Charge}</p>\n<p>你在速度上获得10尺的状态加值。</p>"
        },
        "Spell Effect: Juggernaut of Jagged Stone": {
            "name": "法术效果: 锐石猛车 Juggernaut of Jagged Stone"
        }
    }
}
